[
  {
    "full_name": "nektos/act",
    "stargazers_count": 37987,
    "open_issues_count": 109,
    "forks_count": 961
  },
  {
    "full_name": "go-git/go-git",
    "stargazers_count": 4533,
    "open_issues_count": 433,
    "forks_count": 589
  },
  {
    "full_name": "go-task/task",
    "stargazers_count": 7461,
    "open_issues_count": 193,
    "forks_count": 443
  },
  {
    "full_name": "go-task/task",
    "stargazers_count": 7461,
    "open_issues_count": 193,
    "forks_count": 443
  },
  {
    "full_name": "open-sauced/open-sauced",
    "stargazers_count": 875,
    "open_issues_count": 9,
    "forks_count": 607
  }
]