[
  {
    "full_name": "nektos/act",
    "stargazers_count": 29673,
    "open_issues_count": 79,
    "forks_count": 780
  },
  {
    "full_name": "go-git/go-git",
    "stargazers_count": 4050,
    "open_issues_count": 380,
    "forks_count": 504
  },
  {
    "full_name": "go-task/task",
    "stargazers_count": 6150,
    "open_issues_count": 157,
    "forks_count": 382
  },
  {
    "full_name": "go-task/task",
    "stargazers_count": 6150,
    "open_issues_count": 157,
    "forks_count": 382
  },
  {
    "full_name": "open-sauced/open-sauced",
    "stargazers_count": 812,
    "open_issues_count": 10,
    "forks_count": 448
  }
]