[
  {
    "full_name": "nektos/act",
    "stargazers_count": 40383,
    "open_issues_count": 157,
    "forks_count": 1032
  },
  {
    "full_name": "go-git/go-git",
    "stargazers_count": 4797,
    "open_issues_count": 415,
    "forks_count": 614
  },
  {
    "full_name": "go-task/task",
    "stargazers_count": 8177,
    "open_issues_count": 199,
    "forks_count": 474
  },
  {
    "full_name": "go-task/task",
    "stargazers_count": 8177,
    "open_issues_count": 199,
    "forks_count": 474
  },
  {
    "full_name": "open-sauced/open-sauced",
    "stargazers_count": 886,
    "open_issues_count": 0,
    "forks_count": 683
  }
]