[
  {
    "full_name": "nektos/act",
    "stargazers_count": 70797,
    "open_issues_count": 338,
    "forks_count": 1956
  },
  {
    "full_name": "go-git/go-git",
    "stargazers_count": 7523,
    "open_issues_count": 213,
    "forks_count": 957
  },
  {
    "full_name": "go-task/task",
    "stargazers_count": 15714,
    "open_issues_count": 207,
    "forks_count": 843
  },
  {
    "full_name": "go-task/task",
    "stargazers_count": 15714,
    "open_issues_count": 207,
    "forks_count": 843
  },
  {
    "full_name": "open-sauced/open-sauced",
    "stargazers_count": 953,
    "open_issues_count": 0,
    "forks_count": 1173
  }
]