[
  {
    "full_name": "nektos/act",
    "stargazers_count": 66695,
    "open_issues_count": 269,
    "forks_count": 1771
  },
  {
    "full_name": "go-git/go-git",
    "stargazers_count": 6955,
    "open_issues_count": 150,
    "forks_count": 842
  },
  {
    "full_name": "go-task/task",
    "stargazers_count": 14091,
    "open_issues_count": 431,
    "forks_count": 750
  },
  {
    "full_name": "go-task/task",
    "stargazers_count": 14091,
    "open_issues_count": 431,
    "forks_count": 750
  },
  {
    "full_name": "open-sauced/open-sauced",
    "stargazers_count": 956,
    "open_issues_count": 0,
    "forks_count": 1161
  }
]