[
  {
    "full_name": "nektos/act",
    "stargazers_count": 37174,
    "open_issues_count": 105,
    "forks_count": 934
  },
  {
    "full_name": "go-git/go-git",
    "stargazers_count": 4453,
    "open_issues_count": 443,
    "forks_count": 576
  },
  {
    "full_name": "go-task/task",
    "stargazers_count": 7311,
    "open_issues_count": 184,
    "forks_count": 437
  },
  {
    "full_name": "go-task/task",
    "stargazers_count": 7311,
    "open_issues_count": 184,
    "forks_count": 437
  },
  {
    "full_name": "open-sauced/open-sauced",
    "stargazers_count": 860,
    "open_issues_count": 9,
    "forks_count": 581
  }
]