[
  {
    "full_name": "nektos/act",
    "stargazers_count": 51667,
    "open_issues_count": 204,
    "forks_count": 1296
  },
  {
    "full_name": "go-git/go-git",
    "stargazers_count": 5634,
    "open_issues_count": 320,
    "forks_count": 707
  },
  {
    "full_name": "go-task/task",
    "stargazers_count": 10417,
    "open_issues_count": 285,
    "forks_count": 554
  },
  {
    "full_name": "go-task/task",
    "stargazers_count": 10417,
    "open_issues_count": 285,
    "forks_count": 554
  },
  {
    "full_name": "open-sauced/open-sauced",
    "stargazers_count": 926,
    "open_issues_count": 0,
    "forks_count": 918
  }
]