[
  {
    "full_name": "nektos/act",
    "stargazers_count": 67386,
    "open_issues_count": 275,
    "forks_count": 1797
  },
  {
    "full_name": "go-git/go-git",
    "stargazers_count": 7049,
    "open_issues_count": 173,
    "forks_count": 866
  },
  {
    "full_name": "go-task/task",
    "stargazers_count": 14329,
    "open_issues_count": 302,
    "forks_count": 766
  },
  {
    "full_name": "go-task/task",
    "stargazers_count": 14329,
    "open_issues_count": 302,
    "forks_count": 766
  },
  {
    "full_name": "open-sauced/open-sauced",
    "stargazers_count": 955,
    "open_issues_count": 0,
    "forks_count": 1162
  }
]